pyquicklator/__init__.py
pyquicklator/main.py
pyquicklator/ui.py
pyquicklator/locales/ui_ru.qm
pyquicklator/locales/ui_uk.qm
pyquicklator-1.0.1.dist-info/LICENSE
pyquicklator-1.0.1.dist-info/METADATA
pyquicklator-1.0.1.dist-info/WHEEL
pyquicklator-1.0.1.dist-info/entry_points.txt
pyquicklator-1.0.1.dist-info/top_level.txt
pyquicklator-1.0.1.dist-info/RECORD
