Metadata-Version: 2.1
Name: pyquicklator
Version: 1.0.1
Summary: A fully functional calculator written in PyQt 6 and using sympy for calculations.
Author: limafresh
License: GNU GENERAL PUBLIC LICENSE
Project-URL: Repository, https://github.com/l1mafresh/pyquicklator
Project-URL: Issues, https://github.com/l1mafresh/pyquicklator/issues
Keywords: calculator,project,pyqt,pyqt6,pyqt-calculator,sympy,pip,gui-project
Classifier: Development Status :: 5 - Production/Stable
Classifier: License :: OSI Approved :: GNU General Public License v3 (GPLv3)
Classifier: Programming Language :: Python :: 3
Classifier: Operating System :: OS Independent
Classifier: Intended Audience :: End Users/Desktop
Classifier: Environment :: X11 Applications :: Qt
Classifier: Topic :: Scientific/Engineering :: Mathematics
Classifier: Natural Language :: Ukrainian
Classifier: Natural Language :: Russian
Classifier: Natural Language :: English
Classifier: Topic :: Utilities
Requires-Python: >=3.8
License-File: LICENSE
Requires-Dist: PyQt6 >=6.4.2
Requires-Dist: sympy >=1.13.3
